paramkit/__init__.py
paramkit/cli.py
paramkit/const.py
paramkit/errors.py
paramkit/typing.py
paramkit/utils.py
paramkit/api/__init__.py
paramkit/api/core.py
paramkit/api/fields.py
paramkit/db/__init__.py
paramkit/db/core.py
paramkit/db/model.py
paramkit/docs/__init__.py
paramkit/docs/client.py
paramkit/docs/markdown.py
paramkit/docs/postman.py
paramkit/docs/static/index.html
paramkit/docs/static/index.html.br
paramkit/docs/static/index.html.gz
paramkit/docs/static/_app/env.js
paramkit/docs/static/_app/env.js.br
paramkit/docs/static/_app/env.js.gz
paramkit/docs/static/_app/version.json
paramkit/docs/static/_app/version.json.br
paramkit/docs/static/_app/version.json.gz
paramkit/docs/static/_app/immutable/assets/0.BS116Bd3.css
paramkit/docs/static/_app/immutable/assets/0.BS116Bd3.css.br
paramkit/docs/static/_app/immutable/assets/0.BS116Bd3.css.gz
paramkit/docs/static/_app/immutable/assets/2.CGnGFrAS.css
paramkit/docs/static/_app/immutable/assets/2.CGnGFrAS.css.br
paramkit/docs/static/_app/immutable/assets/2.CGnGFrAS.css.gz
paramkit/docs/static/_app/immutable/assets/_layout.BS116Bd3.css
paramkit/docs/static/_app/immutable/assets/_layout.BS116Bd3.css.br
paramkit/docs/static/_app/immutable/assets/_layout.BS116Bd3.css.gz
paramkit/docs/static/_app/immutable/assets/_page.CGnGFrAS.css
paramkit/docs/static/_app/immutable/assets/_page.CGnGFrAS.css.br
paramkit/docs/static/_app/immutable/assets/_page.CGnGFrAS.css.gz
paramkit/docs/static/_app/immutable/assets/prism.C7jA8Rb8.css
paramkit/docs/static/_app/immutable/assets/prism.C7jA8Rb8.css.br
paramkit/docs/static/_app/immutable/assets/prism.C7jA8Rb8.css.gz
paramkit/docs/static/_app/immutable/assets/vendor.Ln7h645e.css
paramkit/docs/static/_app/immutable/assets/vendor.Ln7h645e.css.br
paramkit/docs/static/_app/immutable/assets/vendor.Ln7h645e.css.gz
paramkit/docs/static/_app/immutable/chunks/Bj4tcL__.js
paramkit/docs/static/_app/immutable/chunks/Bj4tcL__.js.br
paramkit/docs/static/_app/immutable/chunks/Bj4tcL__.js.gz
paramkit-0.2.9.dist-info/METADATA
paramkit-0.2.9.dist-info/WHEEL
paramkit-0.2.9.dist-info/entry_points.txt
paramkit-0.2.9.dist-info/top_level.txt
paramkit-0.2.9.dist-info/RECORD
