Metadata-Version: 2.4
Name: paramkit
Version: 0.2.9
Summary: A parameter management toolkit for Python
Home-page: https://github.com/Dyaln2012516/paramkit
Author: Dylan
Author-email: Dylan <cgq2012516@gmail.com>
License: MIT
Project-URL: Homepage, https://github.com/Dyaln2012516/paramkit
Project-URL: Documentation, https://github.com/Dyaln2012516/paramkit/blob/main/README.md
Project-URL: Issues, https://github.com/Dyaln2012516/paramkit/issues
Keywords: parameters,configuration,management
Classifier: Development Status :: 3 - Alpha
Classifier: Intended Audience :: Developers
Classifier: License :: OSI Approved :: MIT License
Classifier: Programming Language :: Python :: 3
Classifier: Programming Language :: Python :: 3.8
Classifier: Programming Language :: Python :: 3.9
Classifier: Programming Language :: Python :: 3.10
Classifier: Programming Language :: Python :: 3.11
Classifier: Programming Language :: Python :: 3.12
Requires-Python: >=3.8
Requires-Dist: peewee>=3.1.0
Requires-Dist: mdutils>=1.5.0
Requires-Dist: typing-extensions>=4.0.0; python_version < "3.8"
Provides-Extra: test
Requires-Dist: pytest>=7.0; extra == "test"
Requires-Dist: pytest-cov; extra == "test"
Provides-Extra: dev
Requires-Dist: black; extra == "dev"
Requires-Dist: flake8; extra == "dev"
Requires-Dist: mypy; extra == "dev"
Requires-Dist: isort; extra == "dev"
Requires-Dist: pylint; extra == "dev"
Requires-Dist: pycln; extra == "dev"
Dynamic: author
Dynamic: home-page
Dynamic: requires-python
